{
  "project_info": {
    "project_number": "165305436706",
    "project_id": "controlador-fila",
    "storage_bucket": "controlador-fila.appspot.com"
  },
  "client": [
    {
      "client_info": {
        "mobilesdk_app_id": "1:165305436706:android:ba172e54db25cf4874d87b",
        "android_client_info": {
          "package_name": "com.example.gestor_fila"
        }
      },
      "oauth_client": [
        {
          "client_id": "165305436706-uvmavg9g933bkcdm4vv7e2gpjr8uji18.apps.googleusercontent.com",
          "client_type": 3
        }
      ],
      "api_key": [
        {
          "current_key": "AIzaSyBRWf_cwlxo5v86_qMiN2hGkwN_3lSp_ag"
        }
      ],
      "services": {
        "appinvite_service": {
          "other_platform_oauth_client": [
            {
              "client_id": "165305436706-uvmavg9g933bkcdm4vv7e2gpjr8uji18.apps.googleusercontent.com",
              "client_type": 3
            }
          ]
        }
      }
    }
  ],
  "configuration_version": "1"
}